configurer/__init__.py
configurer/__main__.py
tomlconfigurer-0.2.2.dist-info/licenses/LICENSE
tomlconfigurer-0.2.2.dist-info/METADATA
tomlconfigurer-0.2.2.dist-info/WHEEL
tomlconfigurer-0.2.2.dist-info/entry_points.txt
tomlconfigurer-0.2.2.dist-info/top_level.txt
tomlconfigurer-0.2.2.dist-info/RECORD
