Metadata-Version: 2.4
Name: tomlconfigurer
Version: 0.2.2
Summary: A configurer with toml.
Home-page: https://github.com/xystudio889/tomlconfigurer
Author: xystudio
Author-email: xystudio <173288240@qq.com>
License: MIT License
Keywords: config,toml,configure,configurer
Classifier: Programming Language :: Python :: 3
Classifier: License :: OSI Approved :: MIT License
Classifier: Operating System :: OS Independent
Requires-Python: >=3.6
License-File: LICENSE
Requires-Dist: toml>=0.10
Provides-Extra: dev
Dynamic: author
Dynamic: home-page
Dynamic: license-file
Dynamic: requires-python
